{
    "name": "Customer",
    "fields": [
        {
            "fieldName": "name",
            "fieldType": "String"
        },
        {
            "fieldName": "createdBy",
            "fieldType": "String"
        },
        {
            "fieldName": "createdAt",
            "fieldType": "ZonedDateTime"
        },
        {
            "fieldName": "lastUpdatedBy",
            "fieldType": "String"
        },
        {
            "fieldName": "lastUpdatedAt",
            "fieldType": "ZonedDateTime"
        }
    ],
    "relationships": [
        {
            "relationshipType": "one-to-many",
            "otherEntityName": "priceList",
            "otherEntityRelationshipName": "customer",
            "relationshipName": "priceList"
        }
    ],
    "changelogDate": "20191031113536",
    "entityTableName": "customer",
    "dto": "no",
    "pagination": "no",
    "service": "no",
    "jpaMetamodelFiltering": false,
    "fluentMethods": true,
    "readOnly": false,
    "clientRootFolder": "",
    "applications": "*"
}